CsdnBokeGaoxingnengFuwuXitongGoujianYuShijian2017513/README.md
CsdnBokeGaoxingnengFuwuXitongGoujianYuShijian2017513/__init__.py
CsdnBokeGaoxingnengFuwuXitongGoujianYuShijian2017513/__main__.py
CsdnBokeGaoxingnengFuwuXitongGoujianYuShijian2017513/file.epub
CsdnBokeGaoxingnengFuwuXitongGoujianYuShijian2017513/index.html
CsdnBokeGaoxingnengFuwuXitongGoujianYuShijian2017513/css/__init__.py
CsdnBokeGaoxingnengFuwuXitongGoujianYuShijian2017513/css/annotations.css
CsdnBokeGaoxingnengFuwuXitongGoujianYuShijian2017513/css/main.css
CsdnBokeGaoxingnengFuwuXitongGoujianYuShijian2017513/css/normalize.css
CsdnBokeGaoxingnengFuwuXitongGoujianYuShijian2017513/css/popup.css
CsdnBokeGaoxingnengFuwuXitongGoujianYuShijian2017513/font/__init__.py
CsdnBokeGaoxingnengFuwuXitongGoujianYuShijian2017513/font/fontello.eot
CsdnBokeGaoxingnengFuwuXitongGoujianYuShijian2017513/font/fontello.svg
CsdnBokeGaoxingnengFuwuXitongGoujianYuShijian2017513/font/fontello.ttf
CsdnBokeGaoxingnengFuwuXitongGoujianYuShijian2017513/font/fontello.woff
CsdnBokeGaoxingnengFuwuXitongGoujianYuShijian2017513/img/__init__.py
CsdnBokeGaoxingnengFuwuXitongGoujianYuShijian2017513/img/annotator-glyph-sprite.png
CsdnBokeGaoxingnengFuwuXitongGoujianYuShijian2017513/img/annotator-icon-sprite.png
CsdnBokeGaoxingnengFuwuXitongGoujianYuShijian2017513/img/apple-touch-icon.png
CsdnBokeGaoxingnengFuwuXitongGoujianYuShijian2017513/img/cancelfullscreen.png
CsdnBokeGaoxingnengFuwuXitongGoujianYuShijian2017513/img/close.png
CsdnBokeGaoxingnengFuwuXitongGoujianYuShijian2017513/img/fullscreen.png
CsdnBokeGaoxingnengFuwuXitongGoujianYuShijian2017513/img/loader.gif
CsdnBokeGaoxingnengFuwuXitongGoujianYuShijian2017513/img/menu-icon.png
CsdnBokeGaoxingnengFuwuXitongGoujianYuShijian2017513/img/save.png
CsdnBokeGaoxingnengFuwuXitongGoujianYuShijian2017513/img/saved.png
CsdnBokeGaoxingnengFuwuXitongGoujianYuShijian2017513/img/settings-s.png
CsdnBokeGaoxingnengFuwuXitongGoujianYuShijian2017513/img/settings.png
csdn_boke_gaoxingneng_fuwu_xitong_goujian_yu_shijian_2017_5_13-2024.3.2.0.dist-info/METADATA
csdn_boke_gaoxingneng_fuwu_xitong_goujian_yu_shijian_2017_5_13-2024.3.2.0.dist-info/WHEEL
csdn_boke_gaoxingneng_fuwu_xitong_goujian_yu_shijian_2017_5_13-2024.3.2.0.dist-info/entry_points.txt
csdn_boke_gaoxingneng_fuwu_xitong_goujian_yu_shijian_2017_5_13-2024.3.2.0.dist-info/top_level.txt
csdn_boke_gaoxingneng_fuwu_xitong_goujian_yu_shijian_2017_5_13-2024.3.2.0.dist-info/RECORD
